CHANGES.rst
CONTRIBUTORS.rst
MANIFEST.in
README.rst
VERSION
VERSION_SUFFIX
setup.cfg
setup.py
docs/LICENSE-Chosen.md
docs/LICENSE.GPL
docs/LICENSE.rst
docs/index.rst
src/vdz/__init__.py
src/vdz.plone.projectreview.egg-info/PKG-INFO
src/vdz.plone.projectreview.egg-info/SOURCES.txt
src/vdz.plone.projectreview.egg-info/dependency_links.txt
src/vdz.plone.projectreview.egg-info/entry_points.txt
src/vdz.plone.projectreview.egg-info/namespace_packages.txt
src/vdz.plone.projectreview.egg-info/not-zip-safe
src/vdz.plone.projectreview.egg-info/requires.txt
src/vdz.plone.projectreview.egg-info/top_level.txt
src/vdz/plone/__init__.py
src/vdz/plone/projectreview/LIESMICH.TXT
src/vdz/plone/projectreview/__init__.py
src/vdz/plone/projectreview/browser.py
src/vdz/plone/projectreview/config.py
src/vdz/plone/projectreview/configure.zcml
src/vdz/plone/projectreview/data.py
src/vdz/plone/projectreview/dump_schemas
src/vdz/plone/projectreview/interfaces.py
src/vdz/plone/projectreview/mockdata.py
src/vdz/plone/projectreview/oldcrumbs.py
src/vdz/plone/projectreview/profiles.zcml
src/vdz/plone/projectreview/userinfo.py
src/vdz/plone/projectreview/utils.py
src/vdz/plone/projectreview/Extensions/install.py
src/vdz/plone/projectreview/locales/vdz.projectreview.pot
src/vdz/plone/projectreview/locales/de/LC_MESSAGES/vdz.projectreview.po
src/vdz/plone/projectreview/locales/en/LC_MESSAGES/vdz.projectreview.po
src/vdz/plone/projectreview/profiles/default/cssregistry.xml
src/vdz/plone/projectreview/profiles/default/jsregistry.xml
src/vdz/plone/projectreview/profiles/default/metadata.xml
src/vdz/plone/projectreview/profiles/default/rolemap.xml
src/vdz/plone/projectreview/profiles/default/registry/bundles.xml
src/vdz/plone/projectreview/profiles/default/registry/resources.xml
src/vdz/plone/projectreview/profiles/uninstall/cssregistry.xml
src/vdz/plone/projectreview/profiles/uninstall/jsregistry.xml
src/vdz/plone/projectreview/profiles/uninstall/metadata.xml
src/vdz/plone/projectreview/profiles/uninstall/registry/bundles.xml
src/vdz/plone/projectreview/profiles/uninstall/registry/resources.xml
src/vdz/plone/projectreview/sql/LIESMICH
src/vdz/plone/projectreview/sql/fixes-0001.sql
src/vdz/plone/projectreview/sql/fixes-0002.sql
src/vdz/plone/projectreview/sql/schema-witrabau.sql
src/vdz/plone/projectreview/sql/schema-witrabau_journal-pretty.sql
src/vdz/plone/projectreview/sql/schema-witrabau_journal.sql
